http_parse/__init__.py
http_parse/_parser.py
http_parse-0.1.5.dist-info/METADATA
http_parse-0.1.5.dist-info/WHEEL
http_parse-0.1.5.dist-info/RECORD
