Metadata-Version: 2.3
Name: http_parse
Version: 0.1.5
Summary: A simple HTTP request parser.
Project-URL: Homepage, https://github.com/ritiksahni/http_parse
Project-URL: Bug Tracker, https://github.com/ritiksahni/http_parse/issues
Author-email: Ritik Sahni <ritik@ritiksahni.com>
Classifier: License :: OSI Approved :: MIT License
Classifier: Operating System :: OS Independent
Classifier: Programming Language :: Python :: 3
Requires-Python: >=3.7
